<mvc:View controllerName="ShopCart.controller.SubCategories" xmlns:html="http://www.w3.org/1999/xhtml" xmlns:mvc="sap.ui.core.mvc" xmlns="sap.m">
	<App>
		<pages>
			<Page title="Sub Categories">
				<content>
					<List id="subproductsList" >
						<!--items="{ path : 'SUB>/SubCategories'}"-->
						<headerToolbar>
							<Toolbar>
								<SearchField search="onFilter"/>
							</Toolbar>
						</headerToolbar>
						<!--<items>-->
						<!--	<ObjectListItem title="{SUB>CategoryName}" number="{SUB>NumberOfProducts}" type="Active" press="onClick">-->
						<!--	</ObjectListItem>-->
						<!--</items>-->
					</List>
				</content>
			</Page>
		</pages>
	</App>
</mvc:View>